{
  "update_time": "2026-05-01 08:26:18",
  "school_id": "1496",
  "school_name": "重庆工商职业学院",
  "source_url": "https://static-data.gaokao.cn/www/2.0/school/department/1496.json?a=www.gaokao.cn",
  "time": "2025-06-11 17:11:55",
  "md5": "9a9ca328827c150df1dee3950cad62bf",
  "department_count": 6,
  "special_count": 48,
  "data": [
    {
      "department_name": "管理学院",
      "special_num": 10,
      "special": [
        {
          "special_name": "会展策划与管理",
          "level": "专科",
          "school_special_id": "56164"
        },
        {
          "special_name": "供应链运营",
          "level": "专科",
          "school_special_id": "2057292"
        },
        {
          "special_name": "商务英语",
          "level": "专科",
          "school_special_id": "56169"
        },
        {
          "special_name": "工商企业管理",
          "level": "专科",
          "school_special_id": "56154"
        },
        {
          "special_name": "市场营销",
          "level": "专科",
          "school_special_id": "56157"
        },
        {
          "special_name": "旅游管理",
          "level": "专科",
          "school_special_id": "56165"
        },
        {
          "special_name": "现代物流管理",
          "level": "专科",
          "school_special_id": "1468443"
        },
        {
          "special_name": "电子商务",
          "level": "专科",
          "school_special_id": "56163"
        },
        {
          "special_name": "网络营销与直播电商",
          "level": "专科",
          "school_special_id": "1800120"
        },
        {
          "special_name": "连锁经营与管理",
          "level": "专科",
          "school_special_id": "0"
        }
      ]
    },
    {
      "department_name": "会计与金融学院",
      "special_num": 4,
      "special": [
        {
          "special_name": "大数据与会计",
          "level": "专科",
          "school_special_id": "1468446"
        },
        {
          "special_name": "财税大数据应用",
          "level": "专科",
          "school_special_id": "1999861"
        },
        {
          "special_name": "金融服务与管理",
          "level": "专科",
          "school_special_id": "1468444"
        },
        {
          "special_name": "金融科技应用",
          "level": "专科",
          "school_special_id": "1468445"
        }
      ]
    },
    {
      "department_name": "传媒与设计学院",
      "special_num": 9,
      "special": [
        {
          "special_name": "全媒体广告策划与营销",
          "level": "专科",
          "school_special_id": "1468448"
        },
        {
          "special_name": "动漫制作技术",
          "level": "专科",
          "school_special_id": "0"
        },
        {
          "special_name": "广播影视节目制作",
          "level": "专科",
          "school_special_id": "0"
        },
        {
          "special_name": "建筑动画技术",
          "level": "专科",
          "school_special_id": "1468449"
        },
        {
          "special_name": "影视动画",
          "level": "专科",
          "school_special_id": "56146"
        },
        {
          "special_name": "数字媒体技术",
          "level": "专科",
          "school_special_id": "1468447"
        },
        {
          "special_name": "服装与服饰设计",
          "level": "专科",
          "school_special_id": "56150"
        },
        {
          "special_name": "环境艺术设计",
          "level": "专科",
          "school_special_id": "56147"
        },
        {
          "special_name": "网络新闻与传播",
          "level": "专科",
          "school_special_id": "121415"
        }
      ]
    },
    {
      "department_name": "电子信息工程学院",
      "special_num": 6,
      "special": [
        {
          "special_name": "人工智能技术应用",
          "level": "专科",
          "school_special_id": "1468457"
        },
        {
          "special_name": "信息安全技术应用",
          "level": "专科",
          "school_special_id": "2000289"
        },
        {
          "special_name": "应用电子技术",
          "level": "专科",
          "school_special_id": "56145"
        },
        {
          "special_name": "物联网应用技术",
          "level": "专科",
          "school_special_id": "56161"
        },
        {
          "special_name": "现代通信技术",
          "level": "专科",
          "school_special_id": "1468456"
        },
        {
          "special_name": "计算机类(云计算技术应用、大数据技术、软件技术)",
          "level": "专科",
          "school_special_id": "1032868"
        }
      ]
    },
    {
      "department_name": "智能制造与汽车学院",
      "special_num": 9,
      "special": [
        {
          "special_name": "工业机器人技术",
          "level": "专科",
          "school_special_id": "0"
        },
        {
          "special_name": "数字化设计与制造技术",
          "level": "专科",
          "school_special_id": "1800121"
        },
        {
          "special_name": "新能源汽车技术",
          "level": "专科",
          "school_special_id": "0"
        },
        {
          "special_name": "机电一体化技术",
          "level": "专科",
          "school_special_id": "0"
        },
        {
          "special_name": "汽车制造与试验技术",
          "level": "专科",
          "school_special_id": "0"
        },
        {
          "special_name": "汽车智能技术",
          "level": "专科",
          "school_special_id": "1032703"
        },
        {
          "special_name": "汽车检测与维修技术",
          "level": "专科",
          "school_special_id": "56172"
        },
        {
          "special_name": "汽车营销与服务",
          "level": "专科",
          "school_special_id": "0"
        },
        {
          "special_name": "电气自动化技术",
          "level": "专科",
          "school_special_id": "0"
        }
      ]
    },
    {
      "department_name": "城市建设工程学院",
      "special_num": 10,
      "special": [
        {
          "special_name": "城市轨道交通工程技术",
          "level": "专科",
          "school_special_id": "121410"
        },
        {
          "special_name": "工程造价",
          "level": "专科",
          "school_special_id": "121405"
        },
        {
          "special_name": "市政工程技术",
          "level": "专科",
          "school_special_id": "1999984"
        },
        {
          "special_name": "建筑室内设计",
          "level": "专科",
          "school_special_id": "121408"
        },
        {
          "special_name": "建筑室内设计(中美合作办学)",
          "level": "专科",
          "school_special_id": "121408"
        },
        {
          "special_name": "建筑工程技术",
          "level": "专科",
          "school_special_id": "121412"
        },
        {
          "special_name": "建筑设计",
          "level": "专科",
          "school_special_id": "1468453"
        },
        {
          "special_name": "智能光电技术应用",
          "level": "专科",
          "school_special_id": "2153049"
        },
        {
          "special_name": "智能建造技术",
          "level": "专科",
          "school_special_id": "1800119"
        },
        {
          "special_name": "道路与桥梁工程技术",
          "level": "专科",
          "school_special_id": "1468452"
        }
      ]
    }
  ]
}