{
  "update_time": "2026-05-01 08:37:12",
  "school_id": "2529",
  "school_name": "佳木斯职业学院",
  "source_url": "https://static-data.gaokao.cn/www/2.0/school/department/2529.json?a=www.gaokao.cn",
  "time": "2025-06-11 17:12:03",
  "md5": "627c5dbea7e452bffb602f23dfbcfe66",
  "department_count": 9,
  "special_count": 20,
  "data": [
    {
      "department_name": "焊接系",
      "special_num": 1,
      "special": [
        {
          "special_name": "智能焊接技术",
          "level": "专科",
          "school_special_id": "1591385"
        }
      ]
    },
    {
      "department_name": "交通运输系",
      "special_num": 2,
      "special": [
        {
          "special_name": "新能源汽车检测与维修技术",
          "level": "专科",
          "school_special_id": "1591394"
        },
        {
          "special_name": "汽车检测与维修技术",
          "level": "专科",
          "school_special_id": "0"
        }
      ]
    },
    {
      "department_name": "智能制造工程系",
      "special_num": 2,
      "special": [
        {
          "special_name": "数控技术",
          "level": "专科",
          "school_special_id": "135763"
        },
        {
          "special_name": "机电一体化技术",
          "level": "专科",
          "school_special_id": "81652"
        }
      ]
    },
    {
      "department_name": "信息工程系",
      "special_num": 3,
      "special": [
        {
          "special_name": "大数据技术",
          "level": "专科",
          "school_special_id": "0"
        },
        {
          "special_name": "数字媒体艺术设计",
          "level": "专科",
          "school_special_id": "81665"
        },
        {
          "special_name": "环境艺术设计",
          "level": "专科",
          "school_special_id": "81664"
        }
      ]
    },
    {
      "department_name": "现代服务与管理系",
      "special_num": 2,
      "special": [
        {
          "special_name": "大数据与会计",
          "level": "专科",
          "school_special_id": "1591399"
        },
        {
          "special_name": "现代物流管理",
          "level": "专科",
          "school_special_id": "1591401"
        }
      ]
    },
    {
      "department_name": "建筑工程系",
      "special_num": 2,
      "special": [
        {
          "special_name": "工程造价",
          "level": "专科",
          "school_special_id": "81651"
        },
        {
          "special_name": "建筑工程技术",
          "level": "专科",
          "school_special_id": "81647"
        }
      ]
    },
    {
      "department_name": "艺术系",
      "special_num": 2,
      "special": [
        {
          "special_name": "歌舞表演",
          "level": "专科",
          "school_special_id": "81666"
        },
        {
          "special_name": "社会体育",
          "level": "专科",
          "school_special_id": "1888677"
        }
      ]
    },
    {
      "department_name": "护理系",
      "special_num": 3,
      "special": [
        {
          "special_name": "护理",
          "level": "专科",
          "school_special_id": "1591398"
        },
        {
          "special_name": "智慧健康养老服务与管理",
          "level": "专科",
          "school_special_id": "0"
        },
        {
          "special_name": "眼视光技术",
          "level": "专科",
          "school_special_id": "0"
        }
      ]
    },
    {
      "department_name": "教育系",
      "special_num": 3,
      "special": [
        {
          "special_name": "学前教育",
          "level": "专科",
          "school_special_id": "81658"
        },
        {
          "special_name": "小学英语教育",
          "level": "专科",
          "school_special_id": "1798725"
        },
        {
          "special_name": "小学语文教育",
          "level": "专科",
          "school_special_id": "1781964"
        }
      ]
    }
  ]
}