{
  "update_time": "2026-05-01 08:44:02",
  "school_id": "3540",
  "school_name": "长治幼儿师范高等专科学校",
  "source_url": "https://static-data.gaokao.cn/www/2.0/school/department/3540.json?a=www.gaokao.cn",
  "time": "2025-06-11 17:11:57",
  "md5": "84465c6ff3c206988ebbb9bb050adfe2",
  "department_count": 10,
  "special_count": 15,
  "data": [
    {
      "department_name": "学前教育系",
      "special_num": 2,
      "special": [
        {
          "special_name": "学前教育",
          "level": "专科",
          "school_special_id": "1799478"
        },
        {
          "special_name": "幼儿保育",
          "level": "专科",
          "school_special_id": "0"
        }
      ]
    },
    {
      "department_name": "早期教育系",
      "special_num": 2,
      "special": [
        {
          "special_name": "婴幼儿托育服务与管理",
          "level": "专科",
          "school_special_id": "1979082"
        },
        {
          "special_name": "早期教育",
          "level": "专科",
          "school_special_id": "1799477"
        }
      ]
    },
    {
      "department_name": "音乐系",
      "special_num": 1,
      "special": [
        {
          "special_name": "音乐表演",
          "level": "专科",
          "school_special_id": "2162871"
        }
      ]
    },
    {
      "department_name": "舞蹈系",
      "special_num": 1,
      "special": [
        {
          "special_name": "舞蹈教育",
          "level": "专科",
          "school_special_id": "2162872"
        }
      ]
    },
    {
      "department_name": "美术系",
      "special_num": 2,
      "special": [
        {
          "special_name": "美术教育",
          "level": "专科",
          "school_special_id": "1799479"
        },
        {
          "special_name": "艺术设计",
          "level": "专科",
          "school_special_id": "2162873"
        }
      ]
    },
    {
      "department_name": "中文教学部",
      "special_num": 2,
      "special": [
        {
          "special_name": "中文",
          "level": "专科",
          "school_special_id": "1979084"
        },
        {
          "special_name": "研学旅行管理与服务",
          "level": "专科",
          "school_special_id": "2158970"
        }
      ]
    },
    {
      "department_name": "外语教学部",
      "special_num": 1,
      "special": [
        {
          "special_name": "应用英语",
          "level": "专科",
          "school_special_id": "2148547"
        }
      ]
    },
    {
      "department_name": "体育教学部",
      "special_num": 2,
      "special": [
        {
          "special_name": "体能训练",
          "level": "专科",
          "school_special_id": "1472213"
        },
        {
          "special_name": "运动训练",
          "level": "专科",
          "school_special_id": "2162874"
        }
      ]
    },
    {
      "department_name": "健康管理系",
      "special_num": 1,
      "special": [
        {
          "special_name": "智慧健康养老服务与管理",
          "level": "专科",
          "school_special_id": "2158971"
        }
      ]
    },
    {
      "department_name": "信息技术教学部",
      "special_num": 1,
      "special": [
        {
          "special_name": "网络营销与直播电商",
          "level": "专科",
          "school_special_id": "2148546"
        }
      ]
    }
  ]
}