{
  "update_time": "2026-05-01 08:20:26",
  "school_id": "821",
  "school_name": "北京科技职业学院",
  "source_url": "https://static-data.gaokao.cn/www/2.0/school/department/821.json?a=www.gaokao.cn",
  "time": "2025-06-11 17:11:57",
  "md5": "5e6449b2de9401ed664b6c640073ebf8",
  "department_count": 6,
  "special_count": 28,
  "data": [
    {
      "department_name": "技术应用学院",
      "special_num": 8,
      "special": [
        {
          "special_name": "云计算技术与应用",
          "level": "专科",
          "school_special_id": "0"
        },
        {
          "special_name": "大数据技术",
          "level": "专科",
          "school_special_id": "1514162"
        },
        {
          "special_name": "工程造价",
          "level": "专科",
          "school_special_id": "134216"
        },
        {
          "special_name": "无人机应用技术",
          "level": "专科",
          "school_special_id": "1366900"
        },
        {
          "special_name": "汽车检测与维修技术（新能源）",
          "level": "专科",
          "school_special_id": "1514143"
        },
        {
          "special_name": "计算机应用技术",
          "level": "专科",
          "school_special_id": "1028923"
        },
        {
          "special_name": "计算机网络技术",
          "level": "专科",
          "school_special_id": "1028924"
        },
        {
          "special_name": "软件技术",
          "level": "专科",
          "school_special_id": "786769"
        }
      ]
    },
    {
      "department_name": "国际幼教学院",
      "special_num": 4,
      "special": [
        {
          "special_name": "婴幼儿托育服务与管理",
          "level": "专科",
          "school_special_id": "2037642"
        },
        {
          "special_name": "学前教育（园所管理）",
          "level": "专科",
          "school_special_id": "134222"
        },
        {
          "special_name": "学前教育（幼儿双语教育）",
          "level": "专科",
          "school_special_id": "134222"
        },
        {
          "special_name": "学前教育（幼儿艺术教育）",
          "level": "专科",
          "school_special_id": "134222"
        }
      ]
    },
    {
      "department_name": "艺术设计学院",
      "special_num": 5,
      "special": [
        {
          "special_name": "影视多媒体技术（影视多媒体技术）",
          "level": "专科",
          "school_special_id": "134223"
        },
        {
          "special_name": "数字媒体艺术设计（三维数字设计、移动互联网设计）",
          "level": "专科",
          "school_special_id": "1030474"
        },
        {
          "special_name": "电子商务（电商运营、电商设计、电商技术方向）",
          "level": "专科",
          "school_special_id": "1377395"
        },
        {
          "special_name": "艺术设计（数字广告设计）",
          "level": "专科",
          "school_special_id": "2156268"
        },
        {
          "special_name": "艺术设计（环境空间艺术设计）",
          "level": "专科",
          "school_special_id": "2156268"
        }
      ]
    },
    {
      "department_name": "现代服务与管理学院",
      "special_num": 8,
      "special": [
        {
          "special_name": "大数据与会计",
          "level": "专科",
          "school_special_id": "1513583"
        },
        {
          "special_name": "旅游管理（乘务管理）",
          "level": "专科",
          "school_special_id": "134218"
        },
        {
          "special_name": "民航安全技术管理",
          "level": "专科",
          "school_special_id": "1378754"
        },
        {
          "special_name": "汽车检测与维修技术（驾校教练员）",
          "level": "专科",
          "school_special_id": "1514143"
        },
        {
          "special_name": "环境管理与评价",
          "level": "专科",
          "school_special_id": "1861053"
        },
        {
          "special_name": "连锁经营与管理",
          "level": "专科",
          "school_special_id": "1513626"
        },
        {
          "special_name": "酒店管理与数字化运营",
          "level": "专科",
          "school_special_id": "1513745"
        },
        {
          "special_name": "金融科技应用",
          "level": "专科",
          "school_special_id": "0"
        }
      ]
    },
    {
      "department_name": "护理学院",
      "special_num": 2,
      "special": [
        {
          "special_name": "康复治疗技术",
          "level": "专科",
          "school_special_id": "2156560"
        },
        {
          "special_name": "护理",
          "level": "专科",
          "school_special_id": "1513539"
        }
      ]
    },
    {
      "department_name": "昊月国际学院",
      "special_num": 1,
      "special": [
        {
          "special_name": "商务英语",
          "level": "专科",
          "school_special_id": "134221"
        }
      ]
    }
  ]
}